moniza/__init__.py
moniza/moniza.py
moniza/plugins/__init__.py
moniza/plugins/cpu.py
moniza/plugins/cpu_freq.py
moniza/plugins/diskusage.py
moniza/plugins/docker.py
moniza/plugins/gpu.py
moniza/plugins/httpd.py
moniza/plugins/iostat.py
moniza/plugins/loadavg.py
moniza/plugins/memory.py
moniza/plugins/network.py
moniza/plugins/nginx.py
moniza/plugins/phpfpm.py
moniza/plugins/plugins.py
moniza/plugins/process.py
moniza/plugins/swap.py
moniza/plugins/system.py
moniza-0.0.1.data/data/share/doc/moniza/LICENSE
moniza-0.0.1.data/data/share/doc/moniza/README.md
moniza-0.0.1.data/data/share/doc/moniza/moniza-example.ini
moniza-0.0.1.dist-info/LICENSE
moniza-0.0.1.dist-info/METADATA
moniza-0.0.1.dist-info/WHEEL
moniza-0.0.1.dist-info/entry_points.txt
moniza-0.0.1.dist-info/top_level.txt
moniza-0.0.1.dist-info/RECORD
